topology_digital_operations/__init__.py
topology_digital_operations/digital_image.py
topology_digital_operations-1.0.2.dist-info/METADATA
topology_digital_operations-1.0.2.dist-info/WHEEL
topology_digital_operations-1.0.2.dist-info/top_level.txt
topology_digital_operations-1.0.2.dist-info/RECORD
