Metadata-Version: 2.1
Name: topology-digital-operations
Version: 1.0.2
Summary: library for making some operations in digital homotopy theory
Home-page: https://github.com/ksantana97
Author: Karim Jerez
Author-email: ksantana97@gmail.com
Requires-Dist: matplotlib (>=3.5.2)
Requires-Dist: numpy (>=1.21.5)
